odoo8_addon_sale_comment_propagation-8.0.1.0.0-py2.7-nspkg.pth
odoo8_addon_sale_comment_propagation-8.0.1.0.0.dist-info/DESCRIPTION.rst
odoo8_addon_sale_comment_propagation-8.0.1.0.0.dist-info/METADATA
odoo8_addon_sale_comment_propagation-8.0.1.0.0.dist-info/RECORD
odoo8_addon_sale_comment_propagation-8.0.1.0.0.dist-info/WHEEL
odoo8_addon_sale_comment_propagation-8.0.1.0.0.dist-info/metadata.json
odoo8_addon_sale_comment_propagation-8.0.1.0.0.dist-info/namespace_packages.txt
odoo8_addon_sale_comment_propagation-8.0.1.0.0.dist-info/top_level.txt
odoo_addons/sale_comment_propagation/README.rst
odoo_addons/sale_comment_propagation/__init__.py
odoo_addons/sale_comment_propagation/__openerp__.py
odoo_addons/sale_comment_propagation/i18n/es.po
odoo_addons/sale_comment_propagation/i18n/pt_BR.po
odoo_addons/sale_comment_propagation/i18n/ro.po
odoo_addons/sale_comment_propagation/i18n/sl.po
odoo_addons/sale_comment_propagation/images/sale_comments.png
odoo_addons/sale_comment_propagation/models/__init__.py
odoo_addons/sale_comment_propagation/models/account.py
odoo_addons/sale_comment_propagation/models/partner.py
odoo_addons/sale_comment_propagation/models/sale.py
odoo_addons/sale_comment_propagation/models/stock.py
odoo_addons/sale_comment_propagation/static/description/icon.png
odoo_addons/sale_comment_propagation/views/account_view.xml
odoo_addons/sale_comment_propagation/views/partner_view.xml
odoo_addons/sale_comment_propagation/views/sale_view.xml
odoo_addons/sale_comment_propagation/views/stock_view.xml
