Metadata-Version: 2.0
Name: odoo8-addon-sale-comment-propagation
Version: 8.0.1.0.0
Summary: Comments for sale documents (order, picking and invoice)
Home-page: http://www.odoomrp.com
Author: OdooMRP team, AvanzOSC, Serv. Tecnol. Avanzados - Pedro M. Baeza, Odoo Community Association (OCA)
Author-email: support@odoo-community.org
License: UNKNOWN
Platform: UNKNOWN
Classifier: Programming Language :: Python :: 2.7
Classifier: Framework :: Odoo
Requires-Dist: odoo (<9.0a,>=8.0a)
